{
  "alnformat": "bam",
  "ref": "drs://localhost:5050/ref.GRCh38",
  
  "name_0": "HG00443",
  "name_1": "HG00446",
  "name_2": "HG00448",
  "name_3": "HG00449",
  "name_4": "HG00451",
  "name_5": "HG00512",
  "name_6": "HG00513",
  "name_7": "HG00514",
  "name_8": "HG00731",
  "name_9": "HG00732",
  "name_10": "HG00733",
  "name_11": "HG02818",
  "name_12": "HG03125",
  "name_13": "HG03486",
  "name_14": "NA12718",
  "name_15": "NA12748",
  "name_16": "NA12775",
  "name_17": "NA12777",
  "name_18": "NA12778",
  "name_19": "NA12827",

  "aln_0": "drs://localhost:5050/cnest.HG00443.alignment",
  "aln_1": "drs://localhost:5050/cnest.HG00446.alignment",
  "aln_2": "drs://localhost:5050/cnest.HG00448.alignment",
  "aln_3": "drs://localhost:5050/cnest.HG00449.alignment",
  "aln_4": "drs://localhost:5050/cnest.HG00451.alignment",
  "aln_5": "drs://localhost:5050/cnest.HG00512.alignment",
  "aln_6": "drs://localhost:5050/cnest.HG00513.alignment",
  "aln_7": "drs://localhost:5050/cnest.HG00514.alignment",
  "aln_8": "drs://localhost:5050/cnest.HG00731.alignment",
  "aln_9": "drs://localhost:5050/cnest.HG00732.alignment",
  "aln_10": "drs://localhost:5050/cnest.HG00733.alignment",
  "aln_11": "drs://localhost:5050/cnest.HG02818.alignment",
  "aln_12": "drs://localhost:5050/cnest.HG03125.alignment",
  "aln_13": "drs://localhost:5050/cnest.HG03486.alignment",
  "aln_14": "drs://localhost:5050/cnest.NA12718.alignment",
  "aln_15": "drs://localhost:5050/cnest.NA12748.alignment",
  "aln_16": "drs://localhost:5050/cnest.NA12775.alignment",
  "aln_17": "drs://localhost:5050/cnest.NA12777.alignment",
  "aln_18": "drs://localhost:5050/cnest.NA12778.alignment",
  "aln_19": "drs://localhost:5050/cnest.NA12827.alignment",

  "idx_0": "drs://localhost:5050/cnest.HG00443.index",
  "idx_1": "drs://localhost:5050/cnest.HG00446.index",
  "idx_2": "drs://localhost:5050/cnest.HG00448.index",
  "idx_3": "drs://localhost:5050/cnest.HG00449.index",
  "idx_4": "drs://localhost:5050/cnest.HG00451.index",
  "idx_5": "drs://localhost:5050/cnest.HG00512.index",
  "idx_6": "drs://localhost:5050/cnest.HG00513.index",
  "idx_7": "drs://localhost:5050/cnest.HG00514.index",
  "idx_8": "drs://localhost:5050/cnest.HG00731.index",
  "idx_9": "drs://localhost:5050/cnest.HG00732.index",
  "idx_10": "drs://localhost:5050/cnest.HG00733.index",
  "idx_11": "drs://localhost:5050/cnest.HG02818.index",
  "idx_12": "drs://localhost:5050/cnest.HG03125.index",
  "idx_13": "drs://localhost:5050/cnest.HG03486.index",
  "idx_14": "drs://localhost:5050/cnest.NA12718.index",
  "idx_15": "drs://localhost:5050/cnest.NA12748.index",
  "idx_16": "drs://localhost:5050/cnest.NA12775.index",
  "idx_17": "drs://localhost:5050/cnest.NA12777.index",
  "idx_18": "drs://localhost:5050/cnest.NA12778.index",
  "idx_19": "drs://localhost:5050/cnest.NA12827.index"
}
